[{"inputs":[{"internalType":"address payable","name":"_benificiaryAddress","type":"address"}],"stateMutability":"nonpayable","type":"constructor"},{"anonymous":false,"inputs":[{"indexed":false,"internalType":"address","name":"investor","type":"address"},{"indexed":false,"internalType":"uint256","name":"amount","type":"uint256"}],"name":"OnInvest","type":"event"},{"anonymous":false,"inputs":[{"indexed":false,"internalType":"address","name":"investor","type":"address"},{"indexed":false,"internalType":"uint256","name":"amount","type":"uint256"}],"name":"OnWithdraw","type":"event"},{"anonymous":false,"inputs":[{"indexed":true,"internalType":"address","name":"previousOwner","type":"address"},{"indexed":true,"internalType":"address","name":"newOwner","type":"address"}],"name":"OwnershipTransferred","type":"event"},{"inputs":[],"name":"benificiaryAddress","outputs":[{"internalType":"address payable","name":"","type":"address"}],"stateMutability":"view","type":"function"},{"inputs":[{"internalType":"address payable","name":"newAddress","type":"address"}],"name":"changeBenificiary","outputs":[],"stateMutability":"nonpayable","type":"function"},{"inputs":[],"name":"getBalance","outputs":[{"internalType":"uint256","name":"","type":"uint256"}],"stateMutability":"view","type":"function"},{"inputs":[],"name":"getContractInformation","outputs":[{"internalType":"uint256","name":"","type":"uint256"},{"internalType":"uint256","name":"","type":"uint256"},{"internalType":"uint256","name":"","type":"uint256"},{"internalType":"uint256","name":"","type":"uint256"},{"internalType":"uint256","name":"","type":"uint256"}],"stateMutability":"view","type":"function"},{"inputs":[{"internalType":"address","name":"addr","type":"address"}],"name":"getInvestorRefs","outputs":[{"internalType":"uint256","name":"","type":"uint256"},{"internalType":"uint256","name":"","type":"uint256"},{"internalType":"uint256","name":"","type":"uint256"},{"internalType":"uint256","name":"","type":"uint256"},{"internalType":"uint256","name":"","type":"uint256"}],"stateMutability":"view","type":"function"},{"inputs":[{"internalType":"uint256","name":"amount","type":"uint256"},{"internalType":"uint256","name":"maxDays","type":"uint256"},{"internalType":"uint256","name":"perc","type":"uint256"}],"name":"getTotalReturn","outputs":[{"internalType":"uint256","name":"","type":"uint256"}],"stateMutability":"pure","type":"function"},{"inputs":[{"internalType":"address","name":"userAddress","type":"address"}],"name":"getUserAmountOfSpins","outputs":[{"internalType":"uint256","name":"","type":"uint256"}],"stateMutability":"view","type":"function"},{"inputs":[{"internalType":"address","name":"userAddress","type":"address"}],"name":"getUserDividends","outputs":[{"internalType":"uint256","name":"","type":"uint256"}],"stateMutability":"view","type":"function"},{"inputs":[{"internalType":"address","name":"userAddress","type":"address"},{"internalType":"uint256","name":"index","type":"uint256"}],"name":"getUserSpinInfo","outputs":[{"internalType":"uint256","name":"maxDays","type":"uint256"},{"internalType":"uint256","name":"percent","type":"uint256"},{"internalType":"uint256","name":"amount","type":"uint256"},{"internalType":"uint256","name":"totalReturn","type":"uint256"},{"internalType":"uint256","name":"start","type":"uint256"},{"internalType":"uint256","name":"finish","type":"uint256"}],"stateMutability":"view","type":"function"},{"inputs":[{"internalType":"address","name":"_ref","type":"address"}],"name":"invest","outputs":[],"stateMutability":"payable","type":"function"},{"inputs":[{"internalType":"address","name":"","type":"address"}],"name":"investors","outputs":[{"internalType":"address","name":"addr","type":"address"},{"internalType":"address","name":"ref","type":"address"},{"internalType":"uint256","name":"totalInvestment","type":"uint256"},{"internalType":"uint256","name":"totalWithdraw","type":"uint256"},{"internalType":"uint256","name":"totalRef","type":"uint256"},{"internalType":"uint256","name":"investmentCount","type":"uint256"},{"internalType":"uint256","name":"investmentTime","type":"uint256"},{"internalType":"uint256","name":"lastWithdrawDate","type":"uint256"}],"stateMutability":"view","type":"function"},{"inputs":[],"name":"isSpinOpen","outputs":[{"internalType":"bool","name":"","type":"bool"}],"stateMutability":"view","type":"function"},{"inputs":[],"name":"owner","outputs":[{"internalType":"address","name":"","type":"address"}],"stateMutability":"view","type":"function"},{"inputs":[],"name":"renounceOwnership","outputs":[],"stateMutability":"nonpayable","type":"function"},{"inputs":[{"internalType":"bool","name":"_newValue","type":"bool"}],"name":"setIsSpinOpen","outputs":[],"stateMutability":"nonpayable","type":"function"},{"inputs":[],"name":"totalInvested","outputs":[{"internalType":"uint256","name":"","type":"uint256"}],"stateMutability":"view","type":"function"},{"inputs":[],"name":"totalReferralReward","outputs":[{"internalType":"uint256","name":"","type":"uint256"}],"stateMutability":"view","type":"function"},{"inputs":[],"name":"totalSpinCount","outputs":[{"internalType":"uint256","name":"","type":"uint256"}],"stateMutability":"view","type":"function"},{"inputs":[],"name":"totalWithdrawal","outputs":[{"internalType":"uint256","name":"","type":"uint256"}],"stateMutability":"view","type":"function"},{"inputs":[{"internalType":"address","name":"newOwner","type":"address"}],"name":"transferOwnership","outputs":[],"stateMutability":"nonpayable","type":"function"},{"inputs":[],"name":"withdraw","outputs":[],"stateMutability":"nonpayable","type":"function"}]